office365/__init__.py
office365/base_item.py
office365/entity.py
office365/entity_collection.py
office365/graph_client.py
office365/logger.py
office365/communications/__init__.py
office365/communications/cloud_communications.py
office365/communications/callrecords/__init__.py
office365/communications/callrecords/call_record.py
office365/communications/calls/__init__.py
office365/communications/calls/call.py
office365/communications/calls/call_route.py
office365/communications/calls/incoming_context.py
office365/communications/calls/participant.py
office365/communications/calls/participant_info.py
office365/communications/onlinemeetings/__init__.py
office365/communications/onlinemeetings/meeting_participant.py
office365/communications/onlinemeetings/online_meeting.py
office365/communications/onlinemeetings/online_meeting_collection.py
office365/communications/onlinemeetings/online_meeting_provider_type.py
office365/communications/operations/__init__.py
office365/communications/operations/comms_operation.py
office365/communications/presences/__init__.py
office365/communications/presences/presence.py
office365/directory/__init__.py
office365/directory/directory.py
office365/directory/directory_object.py
office365/directory/directory_object_collection.py
office365/directory/directory_role.py
office365/directory/directory_role_template.py
office365/directory/key_credential.py
office365/directory/password_credential.py
office365/directory/profile_photo.py
office365/directory/applications/__init__.py
office365/directory/applications/app_identity.py
office365/directory/applications/app_role_assignment.py
office365/directory/applications/application.py
office365/directory/applications/application_template.py
office365/directory/applications/public_client_application.py
office365/directory/applications/service_principal.py
office365/directory/applications/spa_application.py
office365/directory/applications/web_application.py
office365/directory/audit/__init__.py
Office365_REST_with_timeout-0.1.1.dist-info/LICENSE
Office365_REST_with_timeout-0.1.1.dist-info/METADATA
Office365_REST_with_timeout-0.1.1.dist-info/WHEEL
Office365_REST_with_timeout-0.1.1.dist-info/top_level.txt
Office365_REST_with_timeout-0.1.1.dist-info/RECORD
