Metadata-Version: 2.1
Name: Office365-REST-with-timeout
Version: 0.1.1
Summary: A small example package
Home-page: https://github.com/mmitjansc/Office365-REST-with-timeout
Author: Office365
Author-email: author@example.com
License: UNKNOWN
Project-URL: Bug Tracker, https://github.com/mmitjansc/Office365-REST-with-timeout
Platform: UNKNOWN
Classifier: Programming Language :: Python :: 3
Classifier: License :: OSI Approved :: MIT License
Classifier: Operating System :: OS Independent
Requires-Python: >=3.6
License-File: LICENSE
